easy_regression/__init__.py
easy_regression/deepan_regression_tool.cpython-39-x86_64-linux-gnu.so
easy_regression-0.1.1.dist-info/LICENSE
easy_regression-0.1.1.dist-info/METADATA
easy_regression-0.1.1.dist-info/WHEEL
easy_regression-0.1.1.dist-info/top_level.txt
easy_regression-0.1.1.dist-info/RECORD
