Metadata-Version: 2.1
Name: easy_regression
Version: 0.1.1
Summary: A tool for running and analyzing regression tests
Home-page: https://github.com/DeepanCoder/easy_regression
Author: Deepan Kumar S
Author-email: deepankumar2602@gmail.com
Classifier: Programming Language :: Python :: 3
Classifier: License :: OSI Approved :: MIT License
Classifier: Operating System :: OS Independent
Requires-Python: >=3.6
License-File: LICENSE
Requires-Dist: openpyxl
